{"bytes":25323,"elapsed":"0.151","endpoint-url":"https://github.com/digital-land/development-policy-area-collection/raw/main/data/Buckinghamshire_GIS_Layers/19StrategicEmploymentArea_region.zip","entry-date":"2021-04-17T00:10:30.679681","request-headers":{"Accept":"*/*","Accept-Encoding":"gzip, deflate","Connection":"keep-alive","User-Agent":"Digital Land"},"resource":"6b2628128c516c2e07fc1f45d1794055985a4257dfbfca234bcd4846a2eddc0d","response-headers":{"Accept-Ranges":"bytes","Access-Control-Allow-Origin":"*","Cache-Control":"max-age=300","Connection":"keep-alive","Content-Length":"25323","Content-Security-Policy":"default-src 'none'; style-src 'unsafe-inline'; sandbox","Content-Type":"application/zip","Date":"Sat, 17 Apr 2021 00:10:33 GMT","ETag":"W/\"b1ccbcbbaac1e576230c5d1ba4c4756f1027bb42d1fcb693cc5ac3aba0f980ce\"","Expires":"Sat, 17 Apr 2021 00:15:33 GMT","Source-Age":"0","Strict-Transport-Security":"max-age=31536000","Vary":"Authorization,Accept-Encoding","Via":"1.1 varnish","X-Cache":"MISS","X-Cache-Hits":"0","X-Content-Type-Options":"nosniff","X-Fastly-Request-ID":"334dd3ed7bd8ba06336cf63ba352011e4e0ea915","X-Frame-Options":"deny","X-GitHub-Request-Id":"163C:3AFC:35BCB1:4584EE:607A2779","X-Served-By":"cache-bwi5026-BWI","X-Timer":"S1618618233.183650,VS0,VE67","X-XSS-Protection":"1; mode=block"},"ssl-verify":true,"status":"200"}