{"elapsed":"0.17","endpoint-url":"https://github.com/digital-land/development-policy-area-collection/raw/main/data/Buckinghamshire_GIS_Layers/19NPDawsHill_region.zip","entry-date":"2023-01-29T00:11:50.240007","request-headers":{"Accept":"*/*","Accept-Encoding":"gzip, deflate","Connection":"keep-alive","User-Agent":"DLUHC Digital Land"},"resource":"b1d1b3a145b8f57b54a6227dc8b85cacce48cb9468efb61dbaa978facc48560d","response-headers":{"Accept-Ranges":"bytes","Access-Control-Allow-Origin":"*","Cache-Control":"max-age=300","Connection":"keep-alive","Content-Length":"9388","Content-Security-Policy":"default-src 'none'; style-src 'unsafe-inline'; sandbox","Content-Type":"application/zip","Date":"Sun, 29 Jan 2023 00:11:52 GMT","ETag":"W/\"f72ebe4a1d9f7470dc52359d643aeac20867f9ceba85a756285a71e7a400817b\"","Expires":"Sun, 29 Jan 2023 00:16:52 GMT","Source-Age":"0","Strict-Transport-Security":"max-age=31536000","Vary":"Authorization,Accept-Encoding,Origin","Via":"1.1 varnish","X-Cache":"MISS","X-Cache-Hits":"0","X-Content-Type-Options":"nosniff","X-Fastly-Request-ID":"6a984bca5726c05a3217d645a3a7dccfc2ce7044","X-Frame-Options":"deny","X-GitHub-Request-Id":"4FE6:2376:66F06B:85EA65:63D5B9C8","X-Served-By":"cache-iad-kiad7000127-IAD","X-Timer":"S1674951112.201714,VS0,VE69","X-XSS-Protection":"1; mode=block"},"ssl-verify":true,"status":"200"}