{"elapsed":"0.15","endpoint-url":"https://github.com/digital-land/development-policy-area-collection/raw/main/data/Buckinghamshire_GIS_Layers/19LittleMarlowCountryPark_region.zip","entry-date":"2022-05-20T00:10:43.789130","request-headers":{"Accept":"*/*","Accept-Encoding":"gzip, deflate","Connection":"keep-alive","User-Agent":"DLUHC Digital Land"},"resource":"07c85467a160b0ca3debf5a15f7c72007ee41503bdecd28d19aac050fff23ce0","response-headers":{"Accept-Ranges":"bytes","Access-Control-Allow-Origin":"*","Cache-Control":"max-age=300","Connection":"keep-alive","Content-Length":"6977","Content-Security-Policy":"default-src 'none'; style-src 'unsafe-inline'; sandbox","Content-Type":"application/zip","Date":"Fri, 20 May 2022 00:10:44 GMT","ETag":"W/\"e00dde0449bd9ad57ba2dd79be2a45b47fd58d2179e14c49fb07347bb6cc5360\"","Expires":"Fri, 20 May 2022 00:15:44 GMT","Source-Age":"0","Strict-Transport-Security":"max-age=31536000","Vary":"Authorization,Accept-Encoding,Origin","Via":"1.1 varnish","X-Cache":"MISS","X-Cache-Hits":"0","X-Content-Type-Options":"nosniff","X-Fastly-Request-ID":"9127dc3e283f5ff405992fb0e223c0c440385db8","X-Frame-Options":"deny","X-GitHub-Request-Id":"A354:77F4:256953:3F332A:6286DC84","X-Served-By":"cache-iad-kiad7000133-IAD","X-Timer":"S1653005445.799146,VS0,VE70","X-XSS-Protection":"1; mode=block"},"ssl-verify":true,"status":"200"}