{"elapsed":"0.377","endpoint-url":"https://github.com/digital-land/development-policy-area-collection/raw/main/data/Buckinghamshire_GIS_Layers/19LocalEmploymentArea_region.zip","entry-date":"2023-01-05T00:10:19.160322","request-headers":{"Accept":"*/*","Accept-Encoding":"gzip, deflate","Connection":"keep-alive","User-Agent":"DLUHC Digital Land"},"resource":"1b482d0f57d12f6b3d1e77b040cb28bd47cde5768441422260b4aa6d8812be20","response-headers":{"Accept-Ranges":"bytes","Access-Control-Allow-Origin":"*","Cache-Control":"max-age=300","Connection":"keep-alive","Content-Length":"28831","Content-Security-Policy":"default-src 'none'; style-src 'unsafe-inline'; sandbox","Content-Type":"application/zip","Date":"Thu, 05 Jan 2023 00:10:21 GMT","ETag":"W/\"19fa34fa06390336122b0289bf00d52f041259ed3558745e27ed61cb0dc9a41f\"","Expires":"Thu, 05 Jan 2023 00:15:21 GMT","Source-Age":"0","Strict-Transport-Security":"max-age=31536000","Vary":"Authorization,Accept-Encoding,Origin","Via":"1.1 varnish","X-Cache":"MISS","X-Cache-Hits":"0","X-Content-Type-Options":"nosniff","X-Fastly-Request-ID":"a392930b0aaebc1436cc15f5c0d66c0b07f954c9","X-Frame-Options":"deny","X-GitHub-Request-Id":"0806:23EB:247CA1:302E04:63B6156D","X-Served-By":"cache-dfw-kdfw8210069-DFW","X-Timer":"S1672877422.519420,VS0,VE149","X-XSS-Protection":"1; mode=block"},"ssl-verify":true,"status":"200"}