{"elapsed":"0.15","endpoint-url":"https://github.com/digital-land/development-policy-area-collection/raw/main/data/Buckinghamshire_GIS_Layers/19LowerIcknieldWay_region.zip","entry-date":"2022-09-19T00:12:26.442869","request-headers":{"Accept":"*/*","Accept-Encoding":"gzip, deflate","Connection":"keep-alive","User-Agent":"DLUHC Digital Land"},"resource":"2a0fbb4617763bb2644fa489edcb36942cd07743dce4adfd4791e0ce37ca135a","response-headers":{"Accept-Ranges":"bytes","Access-Control-Allow-Origin":"*","Cache-Control":"max-age=300","Connection":"keep-alive","Content-Length":"2259","Content-Security-Policy":"default-src 'none'; style-src 'unsafe-inline'; sandbox","Content-Type":"application/zip","Date":"Mon, 19 Sep 2022 00:12:27 GMT","ETag":"W/\"7b869ca02697dae201b8b5520d34be90a2b5cf08c6f51c2934f86815243e59a1\"","Expires":"Mon, 19 Sep 2022 00:17:27 GMT","Source-Age":"0","Strict-Transport-Security":"max-age=31536000","Vary":"Authorization,Accept-Encoding,Origin","Via":"1.1 varnish","X-Cache":"MISS","X-Cache-Hits":"0","X-Content-Type-Options":"nosniff","X-Fastly-Request-ID":"127f142cadbcbdc72b606b5fa6e048721d23b2ba","X-Frame-Options":"deny","X-GitHub-Request-Id":"91E2:29F6:7723E3:9E5395:6327B3EB","X-Served-By":"cache-iad-kiad7000095-IAD","X-Timer":"S1663546348.824234,VS0,VE76","X-XSS-Protection":"1; mode=block"},"ssl-verify":true,"status":"200"}