{"bytes":28831,"elapsed":"0.16","endpoint-url":"https://github.com/digital-land/development-policy-area-collection/raw/main/data/Buckinghamshire_GIS_Layers/19LocalEmploymentArea_region.zip","entry-date":"2021-04-12T00:11:51.316376","request-headers":{"Accept":"*/*","Accept-Encoding":"gzip, deflate","Connection":"keep-alive","User-Agent":"Digital Land"},"resource":"1b482d0f57d12f6b3d1e77b040cb28bd47cde5768441422260b4aa6d8812be20","response-headers":{"Accept-Ranges":"bytes","Access-Control-Allow-Origin":"*","Cache-Control":"max-age=300","Connection":"keep-alive","Content-Length":"28831","Content-Security-Policy":"default-src 'none'; style-src 'unsafe-inline'; sandbox","Content-Type":"application/zip","Date":"Mon, 12 Apr 2021 00:11:52 GMT","ETag":"W/\"19fa34fa06390336122b0289bf00d52f041259ed3558745e27ed61cb0dc9a41f\"","Expires":"Mon, 12 Apr 2021 00:16:52 GMT","Source-Age":"0","Strict-Transport-Security":"max-age=31536000","Vary":"Authorization,Accept-Encoding","Via":"1.1 varnish","X-Cache":"MISS","X-Cache-Hits":"0","X-Content-Type-Options":"nosniff","X-Fastly-Request-ID":"887b5a5d86117ea53b132bcdaa019f129afa302a","X-Frame-Options":"deny","X-GitHub-Request-Id":"EDC4:6E42:C3923F:FBC998:60739048","X-Served-By":"cache-bwi5041-BWI","X-Timer":"S1618186313.732229,VS0,VE85","X-XSS-Protection":"1; mode=block"},"ssl-verify":true,"status":"200"}