{"elapsed":"0.368","endpoint-url":"https://github.com/digital-land/development-policy-area-collection/raw/main/data/Buckinghamshire_GIS_Layers/19StrategicEmploymentArea_region.zip","entry-date":"2023-02-26T00:11:28.636396","request-headers":{"Accept":"*/*","Accept-Encoding":"gzip, deflate","Connection":"keep-alive","User-Agent":"DLUHC Digital Land"},"resource":"6b2628128c516c2e07fc1f45d1794055985a4257dfbfca234bcd4846a2eddc0d","response-headers":{"Accept-Ranges":"bytes","Access-Control-Allow-Origin":"*","Cache-Control":"max-age=300","Connection":"keep-alive","Content-Length":"25323","Content-Security-Policy":"default-src 'none'; style-src 'unsafe-inline'; sandbox","Content-Type":"application/zip","Date":"Sun, 26 Feb 2023 00:11:31 GMT","ETag":"W/\"b1ccbcbbaac1e576230c5d1ba4c4756f1027bb42d1fcb693cc5ac3aba0f980ce\"","Expires":"Sun, 26 Feb 2023 00:16:31 GMT","Source-Age":"0","Strict-Transport-Security":"max-age=31536000","Vary":"Authorization,Accept-Encoding,Origin","Via":"1.1 varnish","X-Cache":"MISS","X-Cache-Hits":"0","X-Content-Type-Options":"nosniff","X-Fastly-Request-ID":"21973267c4a4f6136c03dc45ccf74a261736ef05","X-Frame-Options":"deny","X-GitHub-Request-Id":"6C1A:7E64:B0E60E:E54E38:63FAA3B3","X-Served-By":"cache-iad-kiad7000121-IAD","X-Timer":"S1677370291.488960,VS0,VE73","X-XSS-Protection":"1; mode=block"},"ssl-verify":true,"status":"200"}