{"elapsed":"0.162","endpoint-url":"https://github.com/digital-land/development-policy-area-collection/raw/main/data/Buckinghamshire_GIS_Layers/19MolinsSportsGround_region.zip","entry-date":"2022-11-07T00:13:54.598904","request-headers":{"Accept":"*/*","Accept-Encoding":"gzip, deflate","Connection":"keep-alive","User-Agent":"DLUHC Digital Land"},"resource":"39c10fd7bd3348291170173c9a0c783a0108678613ccf51b1088d3ed0f932306","response-headers":{"Accept-Ranges":"bytes","Access-Control-Allow-Origin":"*","Cache-Control":"max-age=300","Connection":"keep-alive","Content-Length":"2082","Content-Security-Policy":"default-src 'none'; style-src 'unsafe-inline'; sandbox","Content-Type":"application/zip","Date":"Mon, 07 Nov 2022 00:13:56 GMT","ETag":"W/\"254a7a36e57f0574d4578a2cc9167e0c9b98b7688b398bd4c4cf6f6cfe38d180\"","Expires":"Mon, 07 Nov 2022 00:18:56 GMT","Source-Age":"0","Strict-Transport-Security":"max-age=31536000","Vary":"Authorization,Accept-Encoding,Origin","Via":"1.1 varnish","X-Cache":"MISS","X-Cache-Hits":"0","X-Content-Type-Options":"nosniff","X-Fastly-Request-ID":"2f2a18c76b578ebf63b412b7bd551be178b0ae68","X-Frame-Options":"deny","X-GitHub-Request-Id":"55F8:084F:69956A:8D6F6B:63684DC4","X-Served-By":"cache-iad-kiad7000155-IAD","X-Timer":"S1667780036.311269,VS0,VE83","X-XSS-Protection":"1; mode=block"},"ssl-verify":true,"status":"200"}