{"elapsed":"0.354","endpoint-url":"https://github.com/digital-land/development-policy-area-collection/raw/main/data/Buckinghamshire_GIS_Layers/19MolinsSportsGround_region.zip","entry-date":"2021-11-19T00:36:39.400200","request-headers":{"Accept":"*/*","Accept-Encoding":"gzip, deflate","Connection":"keep-alive","User-Agent":"Digital Land"},"resource":"39c10fd7bd3348291170173c9a0c783a0108678613ccf51b1088d3ed0f932306","response-headers":{"Accept-Ranges":"bytes","Access-Control-Allow-Origin":"*","Cache-Control":"max-age=300","Connection":"keep-alive","Content-Length":"2082","Content-Security-Policy":"default-src 'none'; style-src 'unsafe-inline'; sandbox","Content-Type":"application/zip","Date":"Fri, 19 Nov 2021 00:36:43 GMT","ETag":"W/\"254a7a36e57f0574d4578a2cc9167e0c9b98b7688b398bd4c4cf6f6cfe38d180\"","Expires":"Fri, 19 Nov 2021 00:41:43 GMT","Source-Age":"0","Strict-Transport-Security":"max-age=31536000","Vary":"Authorization,Accept-Encoding,Origin","Via":"1.1 varnish","X-Cache":"MISS","X-Cache-Hits":"0","X-Content-Type-Options":"nosniff","X-Fastly-Request-ID":"b3b031ce79011a40624ed372afaa40be210319f1","X-Frame-Options":"deny","X-GitHub-Request-Id":"BA34:3B2E:AC516:D7280:6196F19A","X-Served-By":"cache-sea4478-SEA","X-Timer":"S1637282203.874872,VS0,VE184","X-XSS-Protection":"1; mode=block"},"ssl-verify":true,"status":"200"}